setup.py
src/ServerSpecLibrary/__init__.py
src/ServerSpecLibrary/keywords/__init__.py
src/ServerSpecLibrary/keywords/client.py
src/ServerSpecLibrary/keywords/command.py
src/ServerSpecLibrary/keywords/package.py
src/robotframework_serverspeclibrary.egg-info/PKG-INFO
src/robotframework_serverspeclibrary.egg-info/SOURCES.txt
src/robotframework_serverspeclibrary.egg-info/dependency_links.txt
src/robotframework_serverspeclibrary.egg-info/requires.txt
src/robotframework_serverspeclibrary.egg-info/top_level.txt