Metadata-Version: 1.0
Name: robotframework-serverspeclibrary
Version: 0.1
Summary: Server spec on Robot Framework inspired from Serverspec on Ruby
Home-page: https://github.com/wingyplus/robotframework-serverspeclibrary
Author: Thanabodee Charoenpiriyakij
Author-email: wingyminus@gmail.com
License: MIT
Keywords: serverspec robotframework robot
Platform: UNKNOWN
